gemfeed.py
gemfeed-1.1.0.dist-info/LICENSE
gemfeed-1.1.0.dist-info/METADATA
gemfeed-1.1.0.dist-info/WHEEL
gemfeed-1.1.0.dist-info/entry_points.txt
gemfeed-1.1.0.dist-info/top_level.txt
gemfeed-1.1.0.dist-info/RECORD
