Metadata-Version: 2.1
Name: gemfeed
Version: 1.1.0
Summary: Atom feed generating tool for Gemini.
Home-page: https://tildegit.org/solderpunk/gemfeed
Author: Solderpunk
Author-email: solderpunk@sdf.org
License: UNKNOWN
Platform: UNKNOWN
Requires-Dist: feedgen
